djangorestframework_expandable-0.0.6.dist-info/DESCRIPTION.rst
djangorestframework_expandable-0.0.6.dist-info/METADATA
djangorestframework_expandable-0.0.6.dist-info/RECORD
djangorestframework_expandable-0.0.6.dist-info/WHEEL
djangorestframework_expandable-0.0.6.dist-info/metadata.json
djangorestframework_expandable-0.0.6.dist-info/top_level.txt
rest_framework_expandable/__init__.py
rest_framework_expandable/exceptions.py
rest_framework_expandable/serializers.py
rest_framework_expandable/views.py
