Metadata-Version: 2.0
Name: djangorestframework-expandable
Version: 0.0.6
Summary: Mixins for DRF to allow expansion of fields.
Home-page: https://github.com/ovidner/django-rest-framework-expandable
Author: Olle Vidner
Author-email: olle@vidner.se
License: UNKNOWN
Platform: UNKNOWN
Requires-Dist: Django
Requires-Dist: djangorestframework
Requires-Dist: six
